st_annotator/.DS_Store
st_annotator/__init__.py
st_annotator/frontend/.env
st_annotator/frontend/.prettierrc
st_annotator/frontend/build/asset-manifest.json
st_annotator/frontend/build/index.html
st_annotator/frontend/build/static/css/main.aa5cc742.css
st_annotator/frontend/build/static/css/main.aa5cc742.css.map
st_annotator/frontend/build/static/js/main.d1160a7a.js
st_annotator/frontend/build/static/js/main.d1160a7a.js.LICENSE.txt
st_annotator/frontend/build/static/js/main.d1160a7a.js.map
st_annotator/frontend/package-lock.json
st_annotator/frontend/package.json
st_annotator/frontend/public/index.html
st_annotator/frontend/src/components/Annotator.tsx
st_annotator/frontend/src/components/Builder.tsx
st_annotator/frontend/src/helpers/annotatorHelpers.ts
st_annotator/frontend/src/index.css
st_annotator/frontend/src/index.tsx
st_annotator/frontend/src/react-app-env.d.ts
st_annotator/frontend/src/reducers/annotatorReducer.tsx
st_annotator/frontend/src/types/annotatorTypes.ts
st_annotator/frontend/src/utils/StreamlitProvider.tsx
st_annotator/frontend/src/utils/useNullableRenderData.ts
st_annotator/frontend/tailwind.config.js
st_annotator/frontend/tsconfig.json
st_annotator-0.1.3.dist-info/METADATA
st_annotator-0.1.3.dist-info/WHEEL
st_annotator-0.1.3.dist-info/licenses/LICENSE.txt
st_annotator-0.1.3.dist-info/RECORD
