Metadata-Version: 2.4
Name: st-annotator
Version: 0.1.3
Summary: Component for annotating text for Argument Mining and NLP resolution
License: MIT
License-File: LICENSE.txt
Keywords: streamlit,text,annotation,nlp,argument mining,annotator
Author: Ettore Caputo
Author-email: ettore.caputo27@gmail.com
Requires-Python: >=3.8, !=2.7.*, !=3.0.*, !=3.1.*, !=3.2.*, !=3.3.*, !=3.4.*, !=3.5.*, !=3.6.*, !=3.7.*
Classifier: License :: OSI Approved :: MIT License
Classifier: Operating System :: OS Independent
Classifier: Programming Language :: Python :: 3
Classifier: Programming Language :: Python :: 3.8
Classifier: Programming Language :: Python :: 3.9
Classifier: Programming Language :: Python :: 3.10
Classifier: Programming Language :: Python :: 3.11
Classifier: Programming Language :: Python :: 3.12
Classifier: Programming Language :: Python :: 3.13
Classifier: Programming Language :: Python :: 3.14
Requires-Dist: streamlit (>=1.21.0,<2.0.0)
